railway/__init__.py
railway/exceptions.py
railway/postgres/__init__.py
railway/postgres/psycopg2.py
railway-0.0.4.dist-info/METADATA
railway-0.0.4.dist-info/WHEEL
railway-0.0.4.dist-info/top_level.txt
railway-0.0.4.dist-info/RECORD
