Metadata-Version: 2.1
Name: railway
Version: 0.0.4
Summary: Infrastructure, Instantly
Home-page: https://github.com/railwayapp/packages/python
Author: Railway
Author-email: opensource@railway.app
License: UNKNOWN
Platform: UNKNOWN
Classifier: Programming Language :: Python :: 3
Classifier: License :: OSI Approved :: MIT License
Classifier: Operating System :: OS Independent
Requires-Python: >=3.6
